easy_scrap/__init__.py
easy_scrap/scrapper.py
easy_scrap/utils.py
easy_scrap-0.1.0.dist-info/LICENSE
easy_scrap-0.1.0.dist-info/METADATA
easy_scrap-0.1.0.dist-info/WHEEL
easy_scrap-0.1.0.dist-info/top_level.txt
easy_scrap-0.1.0.dist-info/RECORD
