Metadata-Version: 2.1
Name: easy-scrap
Version: 0.1.0
Summary: A small package for scrapping images from google
Author-email: MayStepanyan <mayisstepanyan97@gmail.com>
Project-URL: Homepage, https://github.com/MayStepanyan/easy_scrap
Project-URL: Bug Tracker, https://github.com/MayStepanyan/easy_scrap/issues
Classifier: Programming Language :: Python :: 3
Classifier: License :: OSI Approved :: MIT License
Classifier: Operating System :: Unix
Requires-Python: >=3.7
License-File: LICENSE
Requires-Dist: requests (==2.28.1)
Requires-Dist: pillow (==9.4.0)
